mcp_data_analyzer_zsk/__init__.py
mcp_data_analyzer_zsk/__main__.py
mcp_data_analyzer_zsk/cli.py
mcp_data_analyzer_zsk/core.py
mcp_data_analyzer_zsk-0.1.1.dist-info/licenses/LICENSE
mcp_data_analyzer_zsk-0.1.1.dist-info/METADATA
mcp_data_analyzer_zsk-0.1.1.dist-info/WHEEL
mcp_data_analyzer_zsk-0.1.1.dist-info/entry_points.txt
mcp_data_analyzer_zsk-0.1.1.dist-info/top_level.txt
mcp_data_analyzer_zsk-0.1.1.dist-info/RECORD
