Metadata-Version: 2.4
Name: mcp-data-analyzer-zsk
Version: 0.1.1
Summary: 一个好用的数据分析mcp工具
Requires-Python: >=3.13
License-File: LICENSE
Requires-Dist: mcp[cli]>=1.21.0
Requires-Dist: pandas>=2.3.3
Requires-Dist: seaborn>=0.13.2
Requires-Dist: openpyxl>=3.1.0
Requires-Dist: twine>=6.2.0
Dynamic: license-file
